ckanext/__init__.py
ckanext/transmute/__init__.py
ckanext/transmute/exception.py
ckanext/transmute/interfaces.py
ckanext/transmute/plugin.py
ckanext/transmute/schema.py
ckanext/transmute/transmutators.py
ckanext/transmute/types.py
ckanext/transmute/utils.py
ckanext/transmute/assets/webassets.yml
ckanext/transmute/logic/__init__.py
ckanext/transmute/logic/action/__init__.py
ckanext/transmute/logic/action/get.py
ckanext/transmute/logic/auth/__init__.py
ckanext/transmute/logic/auth/get.py
ckanext/transmute/tests/__init__.py
ckanext/transmute/tests/conftest.py
ckanext/transmute/tests/helpers.py
ckanext/transmute/tests/test_transmutators.py
ckanext/transmute/tests/logic/__init__.py
ckanext/transmute/tests/logic/test_action.py
ckanext_transmute-1.7.0.dist-info/LICENSE
ckanext_transmute-1.7.0.dist-info/METADATA
ckanext_transmute-1.7.0.dist-info/WHEEL
ckanext_transmute-1.7.0.dist-info/entry_points.txt
ckanext_transmute-1.7.0.dist-info/top_level.txt
ckanext_transmute-1.7.0.dist-info/RECORD
